registry/__init__.py
registry/admin.py
registry/apps.py
registry/helper.py
registry/migrations/0001_initial.py
registry/migrations/0002_auto_20200404_0726.py
registry/migrations/__init__.py
registry/models.py
registry/tests.py
registry/views.py
matt_dj_registry-0.2.5.dist-info/LICENSE
matt_dj_registry-0.2.5.dist-info/WHEEL
matt_dj_registry-0.2.5.dist-info/METADATA
matt_dj_registry-0.2.5.dist-info/RECORD
